[{"orientation":"HORIZONTAL","id":"7.2697808455725491721684132903","type":"KEY","tileLength":2,"width":200,"height":100,"gridPosition":{"x":{"startTile":2,"endTile":3},"y":{"startTile":2,"endTile":2}},"left":200,"top":200},{"orientation":"VERTICAL","id":"48.992706235747431721684132903","type":"CANDLE","tileLength":2,"width":100,"height":200,"gridPosition":{"x":{"startTile":2,"endTile":2},"y":{"startTile":0,"endTile":1}},"left":200,"top":0},{"orientation":"VERTICAL","id":"55.3674922459512761721684132903","type":"CANDLE","tileLength":2,"width":100,"height":200,"gridPosition":{"x":{"startTile":0,"endTile":0},"y":{"startTile":1,"endTile":2}},"left":0,"top":100},{"orientation":"VERTICAL","id":"66.25378547652411721684132903","type":"CANDLE","tileLength":2,"width":100,"height":200,"gridPosition":{"x":{"startTile":1,"endTile":1},"y":{"startTile":1,"endTile":2}},"left":100,"top":100},{"orientation":"VERTICAL","id":"72.748167725075381721684132903","type":"CANDLE","tileLength":3,"width":100,"height":300,"gridPosition":{"x":{"startTile":3,"endTile":3},"y":{"startTile":3,"endTile":5}},"left":300,"top":300},{"orientation":"VERTICAL","id":"28.9774936417535051721684132903","type":"CANDLE","tileLength":3,"width":100,"height":300,"gridPosition":{"x":{"startTile":5,"endTile":5},"y":{"startTile":1,"endTile":3}},"left":500,"top":100},{"orientation":"VERTICAL","id":"94.71367608739141721684132903","type":"CANDLE","tileLength":2,"width":100,"height":200,"gridPosition":{"x":{"startTile":4,"endTile":4},"y":{"startTile":1,"endTile":2}},"left":400,"top":100},{"orientation":"HORIZONTAL","id":"36.372100062308311721684132903","type":"CANDLE","tileLength":2,"width":200,"height":100,"gridPosition":{"x":{"startTile":0,"endTile":1},"y":{"startTile":0,"endTile":0}},"left":0,"top":0},{"orientation":"HORIZONTAL","id":"41.9529052475424751721684132903","type":"CANDLE","tileLength":2,"width":200,"height":100,"gridPosition":{"x":{"startTile":3,"endTile":4},"y":{"startTile":0,"endTile":0}},"left":300,"top":0},{"orientation":"HORIZONTAL","id":"47.3436392512070161721684132903","type":"CANDLE","tileLength":2,"width":200,"height":100,"gridPosition":{"x":{"startTile":4,"endTile":5},"y":{"startTile":4,"endTile":4}},"left":400,"top":400}]
